masterqa/__init__.py
masterqa/master_qa.py
masterqa/settings.py
masterqa-1.10.1.dist-info/licenses/LICENSE
masterqa-1.10.1.dist-info/METADATA
masterqa-1.10.1.dist-info/WHEEL
masterqa-1.10.1.dist-info/top_level.txt
masterqa-1.10.1.dist-info/RECORD
