Metadata-Version: 2.4
Name: masterqa
Version: 1.10.1
Summary: Automation-Assisted Manual Testing - https://masterqa.com
Home-page: https://github.com/masterqa/MasterQA
Author: Michael Mintz
Author-email: mdmintz@gmail.com
Maintainer: Michael Mintz
License: MIT
Project-URL: Homepage, https://github.com/masterqa/MasterQA
Project-URL: Download, https://pypi.org/project/masterqa/#files
Project-URL: PyPI, https://pypi.org/project/masterqa/
Project-URL: Source, https://github.com/masterqa/MasterQA
Project-URL: Repository, https://github.com/masterqa/MasterQA
Platform: Windows
Platform: Linux
Platform: Mac OS-X
Requires-Python: >=3.8
License-File: LICENSE
Requires-Dist: seleniumbase>=4.39.4
Requires-Dist: pdbp>=1.7.0
Requires-Dist: tabcompleter>=1.4.0
Requires-Dist: sbvirtualdisplay>=1.4.0
Dynamic: author
Dynamic: author-email
Dynamic: home-page
Dynamic: license
Dynamic: license-file
Dynamic: maintainer
Dynamic: platform
Dynamic: requires-dist
Dynamic: requires-python
Dynamic: summary
